{
    "days": 30,
    "calendar": [
        null,
        {
            "day": 1,
            "farmacia": "Busilacchi"
        },
        {
            "day": 2,
            "farmacia": "Pacini"
        },
        {
            "day": 3,
            "farmacia": "Gismondi"
        },
        {
            "day": 4,
            "farmacia": "Pace"
        },
        {
            "day": 5,
            "farmacia": "La Plaza"
        },
        {
            "day": 6,
            "farmacia": "Del Grecco"
        },
        {
            "day": 7,
            "farmacia": "Bianchini"
        },
        {
            "day": 8,
            "farmacia": "Torres"
        },
        {
            "day": 9,
            "farmacia": "Busilacchi"
        },
        {
            "day": 10,
            "farmacia": "Pacini"
        },
        {
            "day": 11,
            "farmacia": "Gismondi"
        },
        {
            "day": 12,
            "farmacia": "Pace"
        },
        {
            "day": 13,
            "farmacia": "La Plaza"
        },
        {
            "day": 14,
            "farmacia": "Del Grecco"
        },
        {
            "day": 15,
            "farmacia": "Bianchini"
        },
        {
            "day": 16,
            "farmacia": "Torres"
        },
        {
            "day": 17,
            "farmacia": "Busilacchi"
        },
        {
            "day": 18,
            "farmacia": "Pacini"
        },
        {
            "day": 19,
            "farmacia": "Gismondi"
        },
        {
            "day": 20,
            "farmacia": "Pace"
        },
        {
            "day": 21,
            "farmacia": "La Plaza"
        },
        {
            "day": 22,
            "farmacia": "Del Grecco"
        },
        {
            "day": 23,
            "farmacia": "Bianchini"
        },
        {
            "day": 24,
            "farmacia": "Torres"
        },
        {
            "day": 25,
            "farmacia": "Busilacchi"
        },
        {
            "day": 26,
            "farmacia": "Pacini"
        },
        {
            "day": 27,
            "farmacia": "Gismondi"
        },
        {
            "day": 28,
            "farmacia": "Pace"
        },
        {
            "day": 29,
            "farmacia": "La Plaza"
        },
        {
            "day": 30,
            "farmacia": "Del Grecco"
        }
    ]
}